volg/.pypirc
volg/LICENSE
volg/__init__.py
volg/setup.py
volg/volg/__init__.py
volg/volg/core.py
volg-0.1.5.dist-info/METADATA
volg-0.1.5.dist-info/WHEEL
volg-0.1.5.dist-info/RECORD
