Metadata-Version: 2.3
Name: volg
Version: 0.1.5
Summary: A Python package for calculating option Greeks and implied volatility.
License: MIT
Author: Vinod Bhadala
Author-email: vinodbhadala@gmail.com
Requires-Python: >=3.8
Classifier: License :: OSI Approved :: MIT License
Classifier: Programming Language :: Python :: 3
Classifier: Programming Language :: Python :: 3.8
Classifier: Programming Language :: Python :: 3.9
Classifier: Programming Language :: Python :: 3.10
Classifier: Programming Language :: Python :: 3.11
Classifier: Programming Language :: Python :: 3.12
Classifier: Programming Language :: Python :: 3.13
Requires-Dist: numpy
Requires-Dist: pandas
Requires-Dist: scipy
Requires-Dist: setuptools (>=59.6.0)
Project-URL: Homepage, https://github.com/vbhadala/volg
